[
  {
    "dir": "black-&-white",
    "title": "Noirify - Cinema Edition",
    "desc": "MP4, WEBM, MOV supported"
  },
  {
    "dir": "Blur Face",
    "title": "BlurFace Studio - Titan Edition",
    "desc": "No description available."
  },
  {
    "dir": "compress",
    "title": "ImageCompressor Pro v2.2",
    "desc": "Release Ctrl+V to import image"
  },
  {
    "dir": "encoder",
    "title": "Steganography Studio Pro",
    "desc": "Advanced LSB steganography with encryption and compression"
  },
  {
    "dir": "HTML to IMAGE",
    "title": "SnapCode Ultimate | HTML to Image Studio",
    "desc": "Edit HTML on the left. Watch the magic happen on the right."
  },
  {
    "dir": "Image Converter",
    "title": "Convrt.io Pro - Advanced",
    "desc": "No description available."
  },
  {
    "dir": "Image Resizer",
    "title": "ResizrPro - Advanced Image Tool",
    "desc": "Presets"
  },
  {
    "dir": "Image Upscaler",
    "title": "Image Upscaler Pro",
    "desc": "SVG, PNG, JPG or WEBP (MAX. 8000x8000px)"
  },
  {
    "dir": "image-BG",
    "title": "Image Background Remover & Editor",
    "desc": "Upload an image, then compose your scene with powerful layer controls."
  },
  {
    "dir": "imageBGR",
    "title": "Pro Algorithmic BG Remover",
    "desc": "or tap to browse"
  },
  {
    "dir": "imageQE",
    "title": "Image Upscaler Pro",
    "desc": "Enhance your images with AI-powered upscaling"
  },
  {
    "dir": "img-to-pdf",
    "title": "Image to PDF Converter",
    "desc": "Upload, reorder, resize, and rotate your images before conversion."
  },
  {
    "dir": "Meme Generator'",
    "title": "MemeMaster Pro - Ultimate Meme Maker",
    "desc": "No description available."
  },
  {
    "dir": "Multi-Crop",
    "title": "Multi-Crop Tool Pro",
    "desc": "Extract, Name, and Batch Download parts of your image."
  },
  {
    "dir": "Passport Photo Maker",
    "title": "PassportBooth Ultimate - Professional ID Studio",
    "desc": "filename.jpg"
  },
  {
    "dir": "pdf-to-imgs",
    "title": "PDF to Image Converter",
    "desc": "Extract every page from your PDF into high-quality images."
  },
  {
    "dir": "redact",
    "title": "Redact Pro - Secure Image Redaction",
    "desc": "Drag and drop directly here, or click to browse."
  },
  {
    "dir": "rotater",
    "title": "Batch Studio - Ultimate Image Editor",
    "desc": "Live Preview (First Image)"
  },
  {
    "dir": "subtitles",
    "title": "SubtitleGenius - AI Subtitle Generator",
    "desc": ""
  },
  {
    "dir": "Watermark",
    "title": "Watermark Pro - Responsive",
    "desc": "Remove background"
  },
  {
    "dir": "watermark-remover",
    "title": "CleanSlate AI - Extreme",
    "desc": "Drag & Drop an image to start"
  }
]
